csg_pywaapi.py
csg_helpers/AudioFileReader.py
csg_helpers/Files.py
csg_helpers/__init__.py
csg_helpers/gui.py
csg_helpers/soundbank_helper.py
csg_helpers/wwise_settings.py
csg_pywaapi-1.1.20.dist-info/LICENCE
csg_pywaapi-1.1.20.dist-info/METADATA
csg_pywaapi-1.1.20.dist-info/WHEEL
csg_pywaapi-1.1.20.dist-info/top_level.txt
csg_pywaapi-1.1.20.dist-info/RECORD
