Metadata-Version: 2.1
Name: csg-pywaapi
Version: 1.1.20
Summary: Helper package for interfacing with Wwise using waapi. csg_pywaapi is no longer support, please use pss-pywaapi instead
Home-page: https://github.com/simongumbleton/csg_pywaapi
Author: Simon Gumbleton
Author-email: simongumbleton@gmail.com
License: MIT
Platform: UNKNOWN
Classifier: License :: OSI Approved :: MIT License
Classifier: Programming Language :: Python :: 3
License-File: LICENCE
Requires-Dist: waapi-client
Requires-Dist: PyWave
Requires-Dist: pss-pywaapi
